_align.cpython-38-darwin.so
retrieve/__init__.py
retrieve/corpora.py
retrieve/data.py
retrieve/embeddings.py
retrieve/evaluate.py
retrieve/pipeline.py
retrieve/sparse_utils.py
retrieve/utils.py
retrieve/methods/__init__.py
retrieve/methods/pairwise_chunked.py
retrieve/methods/transportation.py
retrieve/methods/wmd.py
retrieve/methods/align/__init__.py
retrieve/methods/align/align.py
retrieve/methods/align/parallel_align.py
retrieve/methods/set_similarity/__init__.py
retrieve/methods/set_similarity/search_index.py
retrieve/methods/set_similarity/set_similarity.py
retrieve/methods/vsm/__init__.py
retrieve/methods/vsm/base.py
retrieve/methods/vsm/embeddings.py
retrieve/methods/vsm/lexical.py
retrieve/methods/vsm/soft_cosine.py
retrieve/resources/__init__.py
retrieve/resources/misc/__init__.py
retrieve/resources/misc/blb.refs.json
retrieve/resources/misc/latin.lemma.ft.dim100.mc2.embeddings.gz
retrieve/resources/misc/new-testament.books
retrieve/resources/misc/old-testament.books
retrieve/resources/stop/__init__.py
retrieve/resources/stop/english.stop
retrieve/resources/stop/greek_berra.stop
retrieve/resources/stop/latin.stop
retrieve/resources/stop/latin_berra.stop
retrieve/resources/texts/__init__.py
retrieve/resources/texts/vulgate.zip
retrieve/viz/__init__.py
retrieve/viz/app.py
retrieve/viz/viz.py
retrieve/viz/static/main.css
retrieve/viz/static/main.js
retrieve/viz/static/tabs.js
retrieve/viz/static/utils.js
retrieve/viz/static/vendor/css/bulma-0.9.0.min.css
retrieve/viz/static/vendor/js/d3-color.v1.min.js
retrieve/viz/static/vendor/js/d3-interpolate.v1.min.js
retrieve/viz/static/vendor/js/d3-scale-chromatic.v1.min.js
retrieve/viz/static/vendor/js/d3.v4.min.js
retrieve/viz/static/vendor/js/jquery-3.5.1.min.js
retrieve/viz/templates/index.html
text_reuse_retrieve-0.1.4.dist-info/LICENSE
text_reuse_retrieve-0.1.4.dist-info/METADATA
text_reuse_retrieve-0.1.4.dist-info/WHEEL
text_reuse_retrieve-0.1.4.dist-info/top_level.txt
text_reuse_retrieve-0.1.4.dist-info/RECORD
