Metadata-Version: 2.1
Name: text-reuse-retrieve
Version: 0.1.4
Summary: A Python package to perform Text Reuse Detection
Home-page: https://github.com/emanjavacas/retrieve
Author: Enrique Manjavacas
Author-email: UNKNOWN
License: MIT
Download-URL: https://github.com/emanjavacas/retrieve/archive/refs/tags/v0.1.4.tar.gz
Platform: UNKNOWN
Classifier: Programming Language :: Python :: 3
Classifier: License :: OSI Approved :: MIT License
Classifier: Operating System :: OS Independent
Requires-Dist: Cython (>=0.29.19)
Requires-Dist: numpy (>=1.17.5)
Requires-Dist: scipy (>=1.4.1)
Requires-Dist: gensim (>=3.8.3)
Requires-Dist: tqdm (>=4.46.0)
Requires-Dist: numba (>=0.49.1)
Requires-Dist: pandas (>=1.0.4)
Requires-Dist: scikit-learn (>=0.23.2)
Requires-Dist: matplotlib (>=3.2.1)
Requires-Dist: Flask (>=1.1.2)
Requires-Dist: SetSimilaritySearch (>=0.1.7dataclasses>=0.6)
